outstaff.py
outstaff-0.1.0.dist-info/METADATA
outstaff-0.1.0.dist-info/WHEEL
outstaff-0.1.0.dist-info/RECORD
